LICENSE
MANIFEST.in
README.md
pyproject.toml
requirements.txt
setup.py
encoref/__init__.py
encoref/_version.py
encoref.egg-info/PKG-INFO
encoref.egg-info/SOURCES.txt
encoref.egg-info/dependency_links.txt
encoref.egg-info/requires.txt
encoref.egg-info/top_level.txt
encoref/core/__init__.py
encoref/core/c_utils.c
encoref/core/c_utils.pyx
encoref/core/dist_funs.py
encoref/core/merger_classes.py
encoref/core/motif_pair_transformations.py
encoref/core/pair_classes.py