Metadata-Version: 2.1
Name: encoref
Version: 0.0.5
Summary: Entity coreference for small data
Home-page: https://github.com/endremborza/encoref
Author: Endre Márk Borza
License: MIT
Platform: any
Classifier: License :: OSI Approved :: MIT License
Requires-Python: >=3.7
